tofi/__init__.py
tofi-0.0.0.dist-info/LICENSE
tofi-0.0.0.dist-info/METADATA
tofi-0.0.0.dist-info/WHEEL
tofi-0.0.0.dist-info/top_level.txt
tofi-0.0.0.dist-info/RECORD
