Metadata-Version: 2.1
Name: tofi
Version: 0.0.0
Summary: I like tofi
Home-page: https://github.com/llandy3d/tofi
Author: Llandy Riveron Del Risco
Author-email: llandy3d@gmail.com
License: UNKNOWN
Platform: UNKNOWN
Classifier: Programming Language :: Python :: 3
Classifier: License :: OSI Approved :: MIT License
Classifier: Operating System :: POSIX :: Linux
Requires-Python: >=3.6
